openapi_client_generator/__init__.py
openapi_client_generator/info.py
openapi_client_generator/py.typed
openapi_client_generator/cli/__init__.py
openapi_client_generator/cli/gen.py
openapi_client_generator/cli/main.py
openapi_client_generator/codegen/__init__.py
openapi_client_generator/codegen/filegen.py
openapi_client_generator/codegen/templates.py
openapi_client_generator/codegen/templates/MANIFEST.in.j2
openapi_client_generator/codegen/templates/README.md.j2
openapi_client_generator/codegen/templates/data_type.py.j2
openapi_client_generator/codegen/templates/endpoint.py.j2
openapi_client_generator/codegen/templates/endpoint_init.py.j2
openapi_client_generator/codegen/templates/generic_init.py.j2
openapi_client_generator/codegen/templates/overrides.py.j2
openapi_client_generator/codegen/templates/package_init.py.j2
openapi_client_generator/codegen/templates/requirements.txt.j2
openapi_client_generator/codegen/templates/service_init.py.j2
openapi_client_generator/codegen/templates/setup.py.j2
openapi_client_generator/common/__init__.py
openapi_client_generator/common/http.py
openapi_client_generator/common/types.py
openapi_client_generator/transformers/__init__.py
openapi_client_generator/transformers/schemas.py
openapi_client_generator-1.0.13.dist-info/LICENSE.txt
openapi_client_generator-1.0.13.dist-info/METADATA
openapi_client_generator-1.0.13.dist-info/WHEEL
openapi_client_generator-1.0.13.dist-info/entry_points.txt
openapi_client_generator-1.0.13.dist-info/top_level.txt
openapi_client_generator-1.0.13.dist-info/RECORD
