Metadata-Version: 2.1
Name: openapi-client-generator
Version: 1.0.13
Summary: OpenAPI Client Generator
Home-page: https://github.com/avanov/openapi-client-generator
Author: Maxim Avanov
Author-email: maxim.avanov@gmail.com
License: UNKNOWN
Keywords: utils typing json yaml openapi oas swagger schema serialization deserialization structured-data
Platform: UNKNOWN
Classifier: Intended Audience :: Developers
Classifier: License :: OSI Approved
Classifier: License :: OSI Approved :: MIT License
Classifier: Programming Language :: Python
Classifier: Programming Language :: Python :: 3
Classifier: Operating System :: POSIX
Requires-Dist: openapi-type (==0.0.21)
Requires-Dist: deepmerge (<0.2,>=0.1.1)
Requires-Dist: typeit
Requires-Dist: jinja2
Requires-Dist: pyrsistent
Requires-Dist: inflection
Requires-Dist: requests
Requires-Dist: black
Provides-Extra: third_party
Requires-Dist: PyYAML (<5.5,>=5.3.1) ; extra == 'third_party'
